matscipy-1.1.1.dist-info/METADATA
matscipy-1.1.1.dist-info/WHEEL
matscipy-1.1.1.dist-info/entry_points.txt
matscipy-1.1.1.dist-info/LICENSE
matscipy/_matscipy.cp39-win_amd64.pyd
matscipy/_matscipy.cp39-win_amd64.dll.a
matscipy/__init__.py
matscipy/_version.py
matscipy/angle_distribution.py
matscipy/atomic_strain.py
matscipy/compat.py
matscipy/deformation.py
matscipy/dislocation.py
matscipy/drift.py
matscipy/elasticity.py
matscipy/ffi.py
matscipy/gamma_surface.py
matscipy/hydrogenate.py
matscipy/logger.py
matscipy/molecules.py
matscipy/neighbours.py
matscipy/numerical.py
matscipy/numpy_tricks.py
matscipy/opls.py
matscipy/optimize.py
matscipy/precon.py
matscipy/pressurecoupling.py
matscipy/rings.py
matscipy/socketcalc.py
matscipy/spatial_correlation_function.py
matscipy/surface.py
matscipy/visualise.py
matscipy/cauchy_born.py
matscipy/surface_reconstruction.py
matscipy/utils.py
matscipy/calculators/__init__.py
matscipy/calculators/calculator.py
matscipy/calculators/fitting.py
matscipy/calculators/supercell_calculator.py
matscipy/calculators/eam/__init__.py
matscipy/calculators/eam/average_atom.py
matscipy/calculators/eam/calculator.py
matscipy/calculators/eam/io.py
matscipy/calculators/ewald/__init__.py
matscipy/calculators/ewald/calculator.py
matscipy/calculators/committee/__init__.py
matscipy/calculators/committee/committee.py
matscipy/calculators/committee/log.py
matscipy/calculators/committee/utils.py
matscipy/calculators/manybody/__init__.py
matscipy/calculators/manybody/calculator.py
matscipy/calculators/manybody/newmb.py
matscipy/calculators/manybody/potentials.py
matscipy/calculators/manybody/explicit_forms/__init__.py
matscipy/calculators/manybody/explicit_forms/harmonic.py
matscipy/calculators/manybody/explicit_forms/kumagai.py
matscipy/calculators/manybody/explicit_forms/stillinger_weber.py
matscipy/calculators/manybody/explicit_forms/tersoff_brenner.py
matscipy/calculators/mcfm/__init__.py
matscipy/calculators/mcfm/calculator.py
matscipy/calculators/mcfm/cluster_data.py
matscipy/calculators/mcfm/qm_cluster.py
matscipy/calculators/mcfm/mcfm_parallel/__init__.py
matscipy-1.1.1.dist-info/RECORD
