Metadata-Version: 2.1
Name: matscipy
Version: 1.1.1
Summary: Generic Python Materials Science tools
Author-Email: James Kermode <james.kermode@gmail.com>, Lars Pastewka <lars.pastewka@imtek.uni-freiburg.de>
License:                   GNU LESSER GENERAL PUBLIC LICENSE
